[{
  "_id": {
    "$oid": "681e8e0c06251d0438d1272f"
  },
  "hu": 0,
  "bet": {
    "$numberLong": "0"
  },
  "win": {
    "$numberLong": "0"
  },
  "lost": {
    "$numberLong": "0"
  },
  "totall": {
    "$numberLong": "0"
  },
  "time": {
    "$numberLong": "0"
  },
  "select": 0,
  "uid": "681e8e0306251d0438d12720",
  "__v": 0
},
{
  "_id": {
    "$oid": "681ed5d42d52453c787eaf21"
  },
  "hu": 1,
  "bet": {
    "$numberLong": "9500000"
  },
  "win": {
    "$numberLong": "58666325"
  },
  "lost": {
    "$numberLong": "2000000"
  },
  "totall": {
    "$numberLong": "56666325"
  },
  "time": {
    "$numberLong": "3428905601604780032"
  },
  "select": 0,
  "uid": "681ed5ca2d52453c787eaf14",
  "__v": 0
},
{
  "_id": {
    "$oid": "681edc39264037351ce6faa9"
  },
  "hu": 0,
  "bet": {
    "$numberLong": "0"
  },
  "win": {
    "$numberLong": "0"
  },
  "lost": {
    "$numberLong": "0"
  },
  "totall": {
    "$numberLong": "0"
  },
  "time": {
    "$numberLong": "0"
  },
  "select": 0,
  "uid": "681edc35264037351ce6fa9a",
  "__v": 0
},
{
  "_id": {
    "$oid": "681f54c24314800dd054cf87"
  },
  "hu": 0,
  "bet": {
    "$numberLong": "0"
  },
  "win": {
    "$numberLong": "0"
  },
  "lost": {
    "$numberLong": "0"
  },
  "totall": {
    "$numberLong": "0"
  },
  "time": {
    "$numberLong": "0"
  },
  "select": 0,
  "uid": "681f54c04314800dd054cf78",
  "__v": 0
},
{
  "_id": {
    "$oid": "6820e4eaef27f2351cda7fb5"
  },
  "hu": 0,
  "bet": {
    "$numberLong": "0"
  },
  "win": {
    "$numberLong": "0"
  },
  "lost": {
    "$numberLong": "0"
  },
  "totall": {
    "$numberLong": "0"
  },
  "time": {
    "$numberLong": "0"
  },
  "select": 0,
  "uid": "6820e4e6ef27f2351cda7f10",
  "__v": 0
},
{
  "_id": {
    "$oid": "6821e7e49e88e91268959e6e"
  },
  "hu": 0,
  "bet": {
    "$numberLong": "0"
  },
  "win": {
    "$numberLong": "0"
  },
  "lost": {
    "$numberLong": "0"
  },
  "totall": {
    "$numberLong": "0"
  },
  "time": {
    "$numberLong": "0"
  },
  "select": 0,
  "uid": "6821e7dd9e88e91268959a06",
  "__v": 0
}]